batch_pystoi/__init__.py
batch_pystoi/stoi.py
batch_pystoi/utils.py
batch_pystoi-0.0.3.dist-info/LICENSE
batch_pystoi-0.0.3.dist-info/METADATA
batch_pystoi-0.0.3.dist-info/WHEEL
batch_pystoi-0.0.3.dist-info/top_level.txt
batch_pystoi-0.0.3.dist-info/RECORD
