Metadata-Version: 2.1
Name: batch_pystoi
Version: 0.0.3
Summary: Short Term Objective Intelligibility metric for batched inputs
Home-page: https://github.com/philgzl/batch-pystoi
Author: Manuel Pariente, Philippe Gonzalez
Author-email: pariente.mnl@gmail.com, hello@philgzl.com
License: MIT
Classifier: Development Status :: 4 - Beta
Classifier: Intended Audience :: Science/Research
Classifier: License :: OSI Approved :: MIT License
Classifier: Programming Language :: Python :: 3
License-File: LICENSE
Requires-Dist: numpy
Requires-Dist: scipy
